download_easy/__init__.py
download_easy/main.py
Download_Easy-0.0.2.dist-info/LICENSE
Download_Easy-0.0.2.dist-info/METADATA
Download_Easy-0.0.2.dist-info/WHEEL
Download_Easy-0.0.2.dist-info/entry_points.txt
Download_Easy-0.0.2.dist-info/top_level.txt
Download_Easy-0.0.2.dist-info/RECORD
