Metadata-Version: 2.1
Name: Download-Easy
Version: 0.0.2
Summary: Download Big or Small files without worry!
Home-page: https://github.com/python-gare/download-easy
Author: Manickam R
License: UNKNOWN
Platform: UNKNOWN
Requires-Python: >=3.6
Requires-Dist: Click
Requires-Dist: tqdm
Requires-Dist: requests
